django_lsp/__init__.py
django_lsp/config.py
django_lsp/py.typed
django_lsp/server.py
django_lsp/core/__init__.py
django_lsp/core/django_setup.py
django_lsp/core/field_analyzer.py
django_lsp/core/model_loader.py
django_lsp/features/__init__.py
django_lsp/features/completion.py
django_lsp/features/diagnostics.py
django_lsp/features/hover.py
django_lsp/features/inlay_hints.py
django_lsp/orm/__init__.py
django_lsp/orm/manager_analyzer.py
django_lsp/orm/operation_provider.py
django_lsp/utils/__init__.py
django_lsp/utils/document_cache.py
django_lsp/utils/documentation.py
django_lsp/utils/logging.py
django_lsp/utils/parser_cache.py
django_lsp/utils/simple_tree_sitter_parser.py
django_qs_lsp-1.4.5.dist-info/METADATA
django_qs_lsp-1.4.5.dist-info/WHEEL
django_qs_lsp-1.4.5.dist-info/entry_points.txt
django_qs_lsp-1.4.5.dist-info/licenses/LICENSE
django_qs_lsp-1.4.5.dist-info/RECORD
