Metadata-Version: 2.4
Name: django-qs-lsp
Version: 1.4.5
Summary: Language Server Protocol implementation for Django ORM operations
Project-URL: Homepage, https://github.com/JBSK8NC/django-lsp
Project-URL: Documentation, https://github.com/JBSK8NC/django-lsp#readme
Project-URL: Repository, https://github.com/JBSK8NC/django-lsp
Project-URL: Issues, https://github.com/JBSK8NC/django-lsp/issues
Author-email: Django LSP Contributors <contributors@django-lsp.dev>
License: MIT
License-File: LICENSE
Classifier: Development Status :: 3 - Alpha
Classifier: Framework :: Django
Classifier: Framework :: Django :: 4.2
Classifier: Framework :: Django :: 5.0
Classifier: Framework :: Django :: 5.1
Classifier: Framework :: Django :: 5.2
Classifier: Intended Audience :: Developers
Classifier: License :: OSI Approved :: MIT License
Classifier: Operating System :: OS Independent
Classifier: Programming Language :: Python :: 3
Classifier: Programming Language :: Python :: 3.10
Classifier: Programming Language :: Python :: 3.11
Classifier: Programming Language :: Python :: 3.12
Classifier: Topic :: Software Development :: Libraries :: Python Modules
Classifier: Topic :: Text Editors :: Integrated Development Environments (IDE)
Requires-Python: >=3.10
Requires-Dist: build>=1.0.0
Requires-Dist: django<6.0,>=4.2
Requires-Dist: lsprotocol>=2023.0.0
Requires-Dist: pygls<2.0,>=1.0.0
Requires-Dist: tree-sitter-python>=0.20.0
Requires-Dist: tree-sitter>=0.20.0
Provides-Extra: build
Requires-Dist: uv>=0.7.12; extra == 'build'
Provides-Extra: dev
Requires-Dist: black>=23.0.0; extra == 'dev'
Requires-Dist: mypy>=1.0.0; extra == 'dev'
Requires-Dist: pre-commit>=3.0.0; extra == 'dev'
Requires-Dist: pytest-asyncio>=0.21.0; extra == 'dev'
Requires-Dist: pytest-cov>=4.0.0; extra == 'dev'
Requires-Dist: pytest-lsp>=0.3.0; extra == 'dev'
Requires-Dist: pytest>=7.0.0; extra == 'dev'
Requires-Dist: python-semantic-release>=10.0.0; extra == 'dev'
Requires-Dist: ruff>=0.3.0; extra == 'dev'
Requires-Dist: twine>=4.0.0; extra == 'dev'
